legacy.py
legacy_test.py
legacy-0.1.7.dist-info/METADATA
legacy-0.1.7.dist-info/WHEEL
legacy-0.1.7.dist-info/top_level.txt
legacy-0.1.7.dist-info/RECORD
